circumplex-0.1.4.dist-info/METADATA
circumplex-0.1.4.dist-info/WHEEL
circumplex-0.1.4.dist-info/licenses/LICENSE
circumplex/__init__.py
circumplex/circumplex.py
circumplex/data/SATP Dataset v1.4.xlsx
circumplex/data/__init__.py
circumplex/data/jz2017.csv
circumplex/datasets.py
circumplex/instrument.py
circumplex/instruments/CSIP.json
circumplex/instruments/SATP-eng.json
circumplex/instruments/SSQP-eng.json
circumplex/instruments/__init__.py
circumplex-0.1.4.dist-info/RECORD
