Metadata-Version: 2.1
Name: circumplex
Version: 0.1.4
Summary: A Python package for analyzing and visualizing circumplex data
Author-Email: Andrew Mitchell <andrew.mitchell.18@ucl.ac.uk>
License: GNU-GPLv3
Project-URL: Repository, https://github.com/MitchellAcoustics/circumplex
Project-URL: Documentation, https://circumplex.readthedocs.io/en/latest/
Requires-Python: >=3.11
Requires-Dist: numpy>=1.25.2
Requires-Dist: matplotlib>=3.8.1
Requires-Dist: scipy>=1.9.3
Requires-Dist: pandas[excel]>=2.1.0
Requires-Dist: pytest>=7.4.3; extra == "test"
Requires-Dist: flake8>=6.1.0; extra == "test"
Requires-Dist: jupyter>=1.0.0; extra == "docs"
Requires-Dist: mkdocs>=1.5.3; extra == "docs"
Requires-Dist: mkdocs-material>=9.4.8; extra == "docs"
Requires-Dist: mkdocstrings[python]>=0.23.0; extra == "docs"
Requires-Dist: mkdocs-jupyter>=0.24.6; extra == "docs"
Requires-Dist: markdown>=3.5.1; extra == "docs"
Requires-Dist: pymdown-extensions>=10.4; extra == "docs"
Requires-Dist: setuptools>=68.2.2; extra == "dev"
Provides-Extra: test
Provides-Extra: docs
Provides-Extra: dev
